COPYING.txt
MANIFEST.in
README.txt
setup.py
sphereTS.py
sphereTSGUI.py
sphereTSGUIhelp.html
sphereTS.egg-info/PKG-INFO
sphereTS.egg-info/SOURCES.txt
sphereTS.egg-info/dependency_links.txt
sphereTS.egg-info/requires.txt
sphereTS.egg-info/top_level.txt