Metadata-Version: 1.1
Name: sphereTS
Version: 1.0
Summary: Calculates the acoustic target strength of an elastic sphere immersed in a fluid
Home-page: https://bitbucket.org/gjm/spherets
Author: Gavin Macaulay
Author-email: gavin@macaulay.co.nz
License: UNKNOWN
Keywords: acoustic TS target strength sphere calibration
Platform: UNKNOWN
Classifier: Development Status :: 4 - Beta
Classifier: Intended Audience :: Science/Research
Classifier: License :: OSI Approved :: GNU General Public License v3 (GPLv3)
Classifier: Operating System :: OS Independent
Classifier: Programming Language :: Python
Classifier: Topic :: Scientific/Engineering
